drone/__init__.py
drone/drone.py
drone_scratch4robots-1.0.3.dist-info/METADATA
drone_scratch4robots-1.0.3.dist-info/RECORD
drone_scratch4robots-1.0.3.dist-info/WHEEL
drone_scratch4robots-1.0.3.dist-info/top_level.txt
