Metadata-Version: 2.1
Name: drone-scratch4robots
Version: 1.0.3
Summary: drone lib for scratch4robots projects
Home-page: https://github.com/JdeRobot/Scratch4Robots
Author: carrionvs
Author-email: carrionvs@gmail.com
License: UNKNOWN
Platform: UNKNOWN
Classifier: Programming Language :: Python
Classifier: License :: OSI Approved :: MIT License
Classifier: Operating System :: OS Independent
Requires-Dist: imutils
